Metadata-Version: 1.0
Name: stupidjoke
Version: 0.2
Summary: The most stupid joke in the world
Home-page: http://github.com/pannkotsky/stupidjoke
Author: Valerii Kovalchuk
Author-email: kovvalole@gmail.com
License: MIT
Platform: UNKNOWN
